feature_importances/__init__.py
feature_importances/feat_imp.py
Unsupervised_Feature_Importances-0.0.9.dist-info/LICENSE
Unsupervised_Feature_Importances-0.0.9.dist-info/METADATA
Unsupervised_Feature_Importances-0.0.9.dist-info/WHEEL
Unsupervised_Feature_Importances-0.0.9.dist-info/top_level.txt
Unsupervised_Feature_Importances-0.0.9.dist-info/RECORD
